README.md
setup.py
fm_lt_tester_lib/__init__.py
fm_lt_tester_lib/functional_modules.py
fm_lt_tester_lib/general_wh_processes.py
fm_lt_tester_lib.egg-info/PKG-INFO
fm_lt_tester_lib.egg-info/SOURCES.txt
fm_lt_tester_lib.egg-info/dependency_links.txt
fm_lt_tester_lib.egg-info/not-zip-safe
fm_lt_tester_lib.egg-info/top_level.txt