Metadata-Version: 1.0
Name: fm-lt-tester-lib
Version: 0.1
Summary: WH Modules
Home-page: UNKNOWN
Author: UNKNOWN
Author-email: UNKNOWN
License: UNKNOWN
Platform: UNKNOWN
